smartpassgen/__init__.py
smartpassgen/generator.py
smartpassgen/words_list.txt
smrtpsg-0.0.2.dist-info/licenses/LICENSE
smrtpsg-0.0.2.dist-info/METADATA
smrtpsg-0.0.2.dist-info/WHEEL
smrtpsg-0.0.2.dist-info/top_level.txt
smrtpsg-0.0.2.dist-info/RECORD
