Metadata-Version: 2.4
Name: smrtpsg
Version: 0.0.2
Summary: A Python library for generating different types of passwords using a simple class interface.
Author-email: Ali Mohamed <aliali1354321@gmail.com>
License-Expression: MIT
Project-URL: Homepage, https://github.com/Alimohamed19/smartpassgen
Classifier: Programming Language :: Python :: 3
Classifier: Operating System :: OS Independent
Requires-Python: >=3.5
License-File: LICENSE
Dynamic: license-file
